heybot/__init__.py
heybot/bot.py
heybot-0.1.0.dist-info/licenses/LICENSE
heybot-0.1.0.dist-info/METADATA
heybot-0.1.0.dist-info/WHEEL
heybot-0.1.0.dist-info/entry_points.txt
heybot-0.1.0.dist-info/top_level.txt
heybot-0.1.0.dist-info/RECORD
