Metadata-Version: 2.4
Name: heybot
Version: 0.1.0
Summary: A simple command-line WhatsApp bot using pywhatkit
Author: Haruki
Author-email: haruki9159826376@gmail.com
Classifier: Programming Language :: Python :: 3
Classifier: License :: OSI Approved :: MIT License
Classifier: Operating System :: OS Independent
Requires-Python: >=3.6
License-File: LICENSE
Requires-Dist: pywhatkit
Dynamic: author
Dynamic: author-email
Dynamic: classifier
Dynamic: license-file
Dynamic: requires-dist
Dynamic: requires-python
Dynamic: summary
